automatic_links/__init__.py
automatic_links/admin.py
automatic_links/apps.py
automatic_links/link.py
automatic_links/models.py
automatic_links/tests.py
automatic_links/utils.py
automatic_links/migrations/0001_initial.py
automatic_links/migrations/__init__.py
automatic_links/templatetags/__init__.py
automatic_links/templatetags/automatic_link_tags.py
django_automatic_links-0.2.7.dist-info/LICENSE
django_automatic_links-0.2.7.dist-info/METADATA
django_automatic_links-0.2.7.dist-info/WHEEL
django_automatic_links-0.2.7.dist-info/top_level.txt
django_automatic_links-0.2.7.dist-info/RECORD
